__init__.py
cats_serialization/__init__.py
cats_serialization/field.py
cats_serialization/interfacies.py
cats_serialization/serializer.py
cats_serialization/validator.py
cats_serialization/lib/__init__.py
cats_serialization/lib/utils.py
cats_serialization-1.1.6.dist-info/LICENSE.txt
cats_serialization-1.1.6.dist-info/METADATA
cats_serialization-1.1.6.dist-info/WHEEL
cats_serialization-1.1.6.dist-info/top_level.txt
cats_serialization-1.1.6.dist-info/RECORD
