Metadata-Version: 2.1
Name: cats-serialization
Version: 1.1.6
Summary: Simple, extensible and functional serializer
Author-email: Vladimir Ordinary <vovikilelik@mail.ru>
License: GNU LESSER GENERAL PUBLIC LICENSE
Project-URL: Homepage, http://git.vovikilelik.com/Clu/cats-serialization-10.git
Project-URL: Bug Tracker, http://git.vovikilelik.com/Clu/cats-serialization-10.git
Classifier: Programming Language :: Python :: 3
Classifier: License :: OSI Approved :: GNU Lesser General Public License v3 or later (LGPLv3+)
Classifier: Operating System :: OS Independent
Requires-Python: >=3.8
License-File: LICENSE.txt
